jules_agent_sdk/__init__.py
jules_agent_sdk/activities.py
jules_agent_sdk/async_base.py
jules_agent_sdk/async_client.py
jules_agent_sdk/base.py
jules_agent_sdk/client.py
jules_agent_sdk/config.py
jules_agent_sdk/exceptions.py
jules_agent_sdk/models.py
jules_agent_sdk/sessions.py
jules_agent_sdk/sources.py
jules_agent_sdk-0.1.0.dist-info/licenses/LICENSE
jules_agent_sdk-0.1.0.dist-info/METADATA
jules_agent_sdk-0.1.0.dist-info/WHEEL
jules_agent_sdk-0.1.0.dist-info/top_level.txt
jules_agent_sdk-0.1.0.dist-info/RECORD
